png_splitter/__init__.py
png_splitter/splitter.py
png_splitter-0.0.5.dist-info/METADATA
png_splitter-0.0.5.dist-info/WHEEL
png_splitter-0.0.5.dist-info/top_level.txt
png_splitter-0.0.5.dist-info/RECORD
