Metadata-Version: 2.1
Name: png-splitter
Version: 0.0.5
Summary: Split a png into smaller images.
Author: andrefpoliveira (André Oliveira)
Author-email: <andre_pinto_oliveira@outlook.pt>
Keywords: python,png,image,splitter
Classifier: Programming Language :: Python :: 3
Classifier: License :: OSI Approved :: MIT License
Classifier: Operating System :: OS Independent
Requires-Dist: Pillow
